sphoin/__init__.py
sphoin/app.py
sphoin/cli.py
sphoin/models/__init__.py
sphoin/models/_indicator.py
sphoin/models/_ohlcv.py
sphoin/models/_study.py
sphoin/plot/__init__.py
sphoin/plot/_plot.py
sphoin/tui/__init__.py
sphoin/tui/widgets/__init__.py
sphoin/tui/widgets/_footer.py
sphoin/tui/widgets/_graph.py
sphoin/tui/widgets/_help.py
sphoin/tui/widgets/_time.py
sphoin/utils/__init__.py
sphoin-2.0.12.dist-info/LICENSE
sphoin-2.0.12.dist-info/METADATA
sphoin-2.0.12.dist-info/WHEEL
sphoin-2.0.12.dist-info/entry_points.txt
sphoin-2.0.12.dist-info/top_level.txt
sphoin-2.0.12.dist-info/zip-safe
sphoin-2.0.12.dist-info/RECORD
