Metadata-Version: 2.1
Name: sphoin
Version: 2.0.12
Summary: Connect to sphoin.app Pro Slots
Home-page: https://github.com/Parsecom/sphoin
Author: P.O.M.
Author-email: office@parsecom.ro
License: MIT license
Keywords: sphoin
Classifier: Development Status :: 5 - Production/Stable
Classifier: Intended Audience :: Developers
Classifier: License :: OSI Approved :: MIT License
Classifier: Natural Language :: English
Classifier: Programming Language :: Python :: 3.6
Classifier: Programming Language :: Python :: 3.7
Classifier: Programming Language :: Python :: 3.8
Classifier: Programming Language :: Python :: 3.9
Classifier: Programming Language :: Python :: 3.10
Classifier: Programming Language :: Python :: 3.11
Requires-Python: >=3.6
License-File: LICENSE
Requires-Dist: requests (==2.28.1)
Requires-Dist: pyyaml (==6.0)
Requires-Dist: textual (==0.15.1)
Requires-Dist: rich (==13.3.3)
Requires-Dist: python-dateutil (==2.8.2)
Requires-Dist: linkify-it-py (==2.0.0)
